quippy/gap_tools.py
quippy/_quippy.cpython-313-darwin.so
quippy/gap_fit
quippy/atoms_module.py
quippy/potential_simple_module.py
quippy/convert.py
quippy/system_module.py
quippy/__init__.py
quippy/dynamicalsystem.py
quippy/nye_tensor_module.py
quippy/nye_tensor.py
quippy/descriptors.py
quippy/descriptors_module.py
quippy/cli.py
quippy/tb_module.py
quippy/potential_module.py
quippy/potential.py
quippy/md
quippy/atoms_types_module.py
quippy/dictionary_module.py
quippy/quip
quippy/dynamicalsystem_module.py
quippy/.dylibs/libopenblasp-r0.3.31.dylib
quippy/.dylibs/liblibAtoms.dylib
quippy/.dylibs/libGAP.dylib
quippy/.dylibs/libgap_fit.dylib
quippy/.dylibs/libfox.dylib
quippy/.dylibs/libgfortran.5.dylib
quippy/.dylibs/libUtils.dylib
quippy/.dylibs/libPotentials.dylib
quippy/.dylibs/libquadmath.0.dylib
quippy/.dylibs/libgcc_s.1.1.dylib
quippy/.dylibs/libgomp.1.dylib
quippy_ase-0.10.2.dist-info/RECORD
quippy_ase-0.10.2.dist-info/WHEEL
quippy_ase-0.10.2.dist-info/entry_points.txt
quippy_ase-0.10.2.dist-info/METADATA
