Metadata-Version: 2.1
Name: quippy-ase
Version: 0.10.2
Summary: ASE-compatible Python bindings for the QUIP and GAP codes
Requires-Python: >=3.9
Requires-Dist: numpy>=2.0
Requires-Dist: ase>=3.17.0
Requires-Dist: f90wrap>=0.3.0
Provides-Extra: dev
Requires-Dist: pytest; extra == "dev"
